{
  "company": {
    "name_jp": "新明和ソフトテクノロジ株式会社",
    "name_en": "Shinmeiwa Soft Technology Co., Ltd.",
    "website": "https://www.shinmeiwa-soft.com/"
  },
  "people": [],
  "social_profiles": [],
  "last_updated": "2026-06-26",
  "search_notes": "No executive information available due to web search limitations and website access restrictions. Company website accessible but requires MiniMax API key for detailed research.",
  "research_notes": "Updated 2026-06-26 via batch processing. Company: 新明和ソフトテクノロジ株式会社. People found: 0. Website: https://www.shinmeiwa-soft.com/. Web search API unavailable (MiniMax key missing) - social profiles could not be researched. Website scraping deferred due to rate limits."
}