{
  "company": {
    "name_jp": "株式会社アローズ・システムズ",
    "name_en": "Arrows Systems Co. Ltd.",
    "website": "https://www.arrows-systems.co.jp/"
  },
  "people": [
    {
      "name": "矢津 達彦",
      "title": "代表取締役社長",
      "linkedin": null,
      "twitter": null,
      "department": "",
      "email": ""
    }
  ],
  "social_profiles": [
    {
      "platform": "Instagram",
      "url": "https://www.instagram.com/arrowssystems/"
    }
  ],
  "last_updated": "2026-06-26",
  "research_notes": "1999年2月設立。資本金6,132万円。従業員単体169名、グループ計263名。みなとみらい所在。グループ企業：株式会社宿研、株式会社良地良宿、minato coffee。"
}
