{
  "company_name": "有限会社スパイスメディア (Spice Media LLC)",
  "english_name": "Spice Media LLC",
  "key_people": [],
  "executives": [],
  "technical_leads": [],
  "business_contacts": [],
  "research_notes": "Updated 2026-06-26 via batch processing. Company: Unknown. People found: 0. Website: . Web search API unavailable (MiniMax key missing) - social profiles could not be researched. Website scraping deferred due to rate limits.",
  "contact_potential": {
    "executive_team": "Unknown",
    "technical_team": "Unknown",
    "business_development": "Unknown",
    "partnership_contacts": "Unknown"
  },
  "last_updated": "2026-06-26",
  "research_status": "placeholder",
  "estimated_research_completion": "Pending web search functionality restoration"
}