{
  "company": {
    "name": "株式会社システムハウス・アイエヌジー 横浜支店（System House I.N.G.）",
    "name_en": "",
    "website": ""
  },
  "people": [
    {
      "name": "村越伸夫",
      "title": "代表取締役社長",
      "linkedin": "https://www.linkedin.com/in/聖人-村越-8b16b09b/",
      "twitter": null
    }
  ],
  "last_updated": "2026-06-26",
  "data_source": "tavily_ai_summary",
  "research_notes": "Updated 2026-06-26 via batch processing. Company: Unknown. People found: 1. Website: . Web search API unavailable (MiniMax key missing) - social profiles could not be researched. Website scraping deferred due to rate limits."
}